dlsproc/__init__.py
dlsproc/_nbdev.py
dlsproc/assemble.py
dlsproc/bundle.py
dlsproc/core.py
dlsproc/extend.py
dlsproc/hier.py
dlsproc/io.py
dlsproc/parse.py
dlsproc/postprocess.py
dlsproc/structure.py
dlsproc/xml.py
dlsproc-0.0.4.dist-info/LICENSE
dlsproc-0.0.4.dist-info/METADATA
dlsproc-0.0.4.dist-info/WHEEL
dlsproc-0.0.4.dist-info/entry_points.txt
dlsproc-0.0.4.dist-info/top_level.txt
dlsproc-0.0.4.dist-info/RECORD
