Metadata-Version: 2.1
Name: dlsproc
Version: 0.0.4
Summary: Download Spanish procurement
Home-page: https://github.com/manuvazquez/dlsproc/tree/master/
Author: Manuel A. Vázquez
Author-email: manuavazquez@gmail.com
License: Apache Software License 2.0
Keywords: Spain procurement
Platform: UNKNOWN
Classifier: Development Status :: 3 - Alpha
Classifier: Intended Audience :: Developers
Classifier: Natural Language :: English
Classifier: Programming Language :: Python :: 3.10
Classifier: License :: OSI Approved :: Apache Software License
Requires-Python: >=3.10
License-File: LICENSE
Requires-Dist: pip
Requires-Dist: packaging
Requires-Dist: python-magic
Requires-Dist: html2text
Requires-Dist: colorama
Requires-Dist: pyyaml
Requires-Dist: lxml
Requires-Dist: pandas
Requires-Dist: pyarrow
Provides-Extra: dev
